batdata/__init__.py
batdata/exceptions.py
batdata/http.py
batdata/models.py
batdata/vndData/__init__.py
batdata/vndData/funcLookup.py
batdata/vndData/taskManagement.py
batdata/vndData/utils.py
batdata/vndData/vnd.py
batdata/vndData/vndApi.py
batdata-0.1.0.dist-info/LICENSE
batdata-0.1.0.dist-info/METADATA
batdata-0.1.0.dist-info/WHEEL
batdata-0.1.0.dist-info/top_level.txt
batdata-0.1.0.dist-info/RECORD
