Metadata-Version: 2.1
Name: batdata
Version: 0.1.0
Summary: A package to download Vietnam stock market data
Home-page: UNKNOWN
Author: Bien An Toan
Author-email: batdata@bienantoam.com.vn
License: UNKNOWN
Platform: UNKNOWN
Classifier: Programming Language :: Python :: 3
Classifier: License :: OSI Approved :: MIT License
Classifier: Operating System :: OS Independent
Requires-Dist: pandas (>=0.24.1)
Requires-Dist: requests (>=2.21.0)
